[
  {
    "date": "2024-11-29",
    "symbol": "ADBE",
    "reportedCurrency": "USD",
    "cik": "0000796343",
    "fillingDate": "2024-11-29",
    "acceptedDate": "2024-11-29 00:00:00",
    "calendarYear": "2024",
    "period": "FY",
    "netIncome": 5560000000,
    "depreciationAndAmortization": 894000000,
    "deferredIncomeTax": -341000000,
    "stockBasedCompensation": 1881000000,
    "changeInWorkingCapital": 144000000,
    "accountsReceivables": 0,
    "inventory": 0,
    "accountsPayables": 0,
    "otherWorkingCapital": 144000000,
    "otherNonCashItems": -82000000,
    "netCashProvidedByOperatingActivities": 8056000000,
    "investmentsInPropertyPlantAndEquipment": -232000000,
    "acquisitionsNet": 0,
    "purchasesOfInvestments": -58000000,
    "salesMaturitiesOfInvestments": 388000000,
    "otherInvestingActivites": 51000000,
    "netCashUsedForInvestingActivites": 149000000,
    "debtRepayment": 1997000000,
    "commonStockIssued": 209000000,
    "commonStockRepurchased": -9500000000,
    "dividendsPaid": 0,
    "otherFinancingActivites": -430000000,
    "netCashUsedProvidedByFinancingActivities": -7724000000,
    "effectOfForexChangesOnCash": -9000000,
    "netChangeInCash": 472000000,
    "cashAtEndOfPeriod": 7613000000,
    "cashAtBeginningOfPeriod": 7141000000,
    "operatingCashFlow": 8056000000,
    "capitalExpenditure": -232000000,
    "freeCashFlow": 7824000000,
    "link": "https://www.sec.gov/Archives/edgar/data/796343/000079634325000004/0000796343-25-000004-index.htm",
    "finalLink": "https://www.sec.gov/Archives/edgar/data/796343/000079634325000004/adbe-20241129.htm"
  },
  {
    "date": "2023-12-01",
    "symbol": "ADBE",
    "reportedCurrency": "USD",
    "cik": "0000796343",
    "fillingDate": "2024-01-17",
    "acceptedDate": "2024-01-16 20:01:55",
    "calendarYear": "2023",
    "period": "FY",
    "netIncome": 5428000000,
    "depreciationAndAmortization": 872000000,
    "deferredIncomeTax": -426000000,
    "stockBasedCompensation": 1718000000,
    "changeInWorkingCapital": -355000000,
    "accountsReceivables": -159000000,
    "inventory": 208000000,
    "accountsPayables": -49000000,
    "otherWorkingCapital": -355000000,
    "otherNonCashItems": 65000000,
    "netCashProvidedByOperatingActivities": 7302000000,
    "investmentsInPropertyPlantAndEquipment": -360000000,
    "acquisitionsNet": 0,
    "purchasesOfInvestments": -53000000,
    "salesMaturitiesOfInvestments": 1189000000,
    "otherInvestingActivites": 0,
    "netCashUsedForInvestingActivites": 776000000,
    "debtRepayment": -500000000,
    "commonStockIssued": 314000000,
    "commonStockRepurchased": -4400000000,
    "dividendsPaid": 0,
    "otherFinancingActivites": -596000000,
    "netCashUsedProvidedByFinancingActivities": -5182000000,
    "effectOfForexChangesOnCash": 9000000,
    "netChangeInCash": 2905000000,
    "cashAtEndOfPeriod": 7141000000,
    "cashAtBeginningOfPeriod": 4236000000,
    "operatingCashFlow": 7302000000,
    "capitalExpenditure": -360000000,
    "freeCashFlow": 6942000000,
    "link": "https://www.sec.gov/Archives/edgar/data/796343/000079634324000006/0000796343-24-000006-index.htm",
    "finalLink": "https://www.sec.gov/Archives/edgar/data/796343/000079634324000006/adbe-20231201.htm"
  },
  {
    "date": "2022-12-02",
    "symbol": "ADBE",
    "reportedCurrency": "USD",
    "cik": "0000796343",
    "fillingDate": "2023-01-17",
    "acceptedDate": "2023-01-17 16:34:00",
    "calendarYear": "2022",
    "period": "FY",
    "netIncome": 4756000000,
    "depreciationAndAmortization": 856000000,
    "deferredIncomeTax": 328000000,
    "stockBasedCompensation": 1440000000,
    "changeInWorkingCapital": 336000000,
    "accountsReceivables": -198000000,
    "inventory": 0,
    "accountsPayables": 66000000,
    "otherWorkingCapital": 468000000,
    "otherNonCashItems": 122000000,
    "netCashProvidedByOperatingActivities": 7838000000,
    "investmentsInPropertyPlantAndEquipment": -442000000,
    "acquisitionsNet": -126000000,
    "purchasesOfInvestments": -955000000,
    "salesMaturitiesOfInvestments": 953000000,
    "otherInvestingActivites": -2000000,
    "netCashUsedForInvestingActivites": -570000000,
    "debtRepayment": 0,
    "commonStockIssued": 278000000,
    "commonStockRepurchased": -6550000000,
    "dividendsPaid": 0,
    "otherFinancingActivites": -553000000,
    "netCashUsedProvidedByFinancingActivities": -6825000000,
    "effectOfForexChangesOnCash": -51000000,
    "netChangeInCash": 392000000,
    "cashAtEndOfPeriod": 4236000000,
    "cashAtBeginningOfPeriod": 3844000000,
    "operatingCashFlow": 7838000000,
    "capitalExpenditure": -442000000,
    "freeCashFlow": 7396000000,
    "link": "https://www.sec.gov/Archives/edgar/data/796343/000079634323000007/0000796343-23-000007-index.htm",
    "finalLink": "https://www.sec.gov/Archives/edgar/data/796343/000079634323000007/adbe-20221202.htm"
  },
  {
    "date": "2021-12-03",
    "symbol": "ADBE",
    "reportedCurrency": "USD",
    "cik": "0000796343",
    "fillingDate": "2022-01-21",
    "acceptedDate": "2022-01-21 16:03:34",
    "calendarYear": "2021",
    "period": "FY",
    "netIncome": 4822000000,
    "depreciationAndAmortization": 788000000,
    "deferredIncomeTax": 183000000,
    "stockBasedCompensation": 1069000000,
    "changeInWorkingCapital": 285000000,
    "accountsReceivables": -430000000,
    "inventory": 450000000,
    "accountsPayables": -20000000,
    "otherWorkingCapital": 285000000,
    "otherNonCashItems": 76000000,
    "netCashProvidedByOperatingActivities": 7223000000,
    "investmentsInPropertyPlantAndEquipment": -330000000,
    "acquisitionsNet": -2682000000,
    "purchasesOfInvestments": -1575000000,
    "salesMaturitiesOfInvestments": 1068000000,
    "otherInvestingActivites": -507000000,
    "netCashUsedForInvestingActivites": -3519000000,
    "debtRepayment": 0,
    "commonStockIssued": 291000000,
    "commonStockRepurchased": -3950000000,
    "dividendsPaid": 0,
    "otherFinancingActivites": -642000000,
    "netCashUsedProvidedByFinancingActivities": -4301000000,
    "effectOfForexChangesOnCash": -37000000,
    "netChangeInCash": -634000000,
    "cashAtEndOfPeriod": 3844000000,
    "cashAtBeginningOfPeriod": 4478000000,
    "operatingCashFlow": 7223000000,
    "capitalExpenditure": -330000000,
    "freeCashFlow": 6893000000,
    "link": "https://www.sec.gov/Archives/edgar/data/796343/000079634322000032/0000796343-22-000032-index.htm",
    "finalLink": "https://www.sec.gov/Archives/edgar/data/796343/000079634322000032/adbe-20211203.htm"
  },
  {
    "date": "2020-11-27",
    "symbol": "ADBE",
    "reportedCurrency": "USD",
    "cik": "0000796343",
    "fillingDate": "2021-01-15",
    "acceptedDate": "2021-01-15 16:03:42",
    "calendarYear": "2020",
    "period": "FY",
    "netIncome": 5260000000,
    "depreciationAndAmortization": 757000000,
    "deferredIncomeTax": -1501000000,
    "stockBasedCompensation": 909000000,
    "changeInWorkingCapital": 186000000,
    "accountsReceivables": 106000000,
    "inventory": -202000000,
    "accountsPayables": 96000000,
    "otherWorkingCapital": 186000000,
    "otherNonCashItems": 116000000,
    "netCashProvidedByOperatingActivities": 5727000000,
    "investmentsInPropertyPlantAndEquipment": -419000000,
    "acquisitionsNet": 0,
    "purchasesOfInvestments": -221000000,
    "salesMaturitiesOfInvestments": 1091000000,
    "otherInvestingActivites": -865000000,
    "netCashUsedForInvestingActivites": -414000000,
    "debtRepayment": -6000000,
    "commonStockIssued": 270000000,
    "commonStockRepurchased": -3050000000,
    "dividendsPaid": 0,
    "otherFinancingActivites": -702000000,
    "netCashUsedProvidedByFinancingActivities": -3488000000,
    "effectOfForexChangesOnCash": 3000000,
    "netChangeInCash": 1828000000,
    "cashAtEndOfPeriod": 4478000000,
    "cashAtBeginningOfPeriod": 2650000000,
    "operatingCashFlow": 5727000000,
    "capitalExpenditure": -419000000,
    "freeCashFlow": 5308000000,
    "link": "https://www.sec.gov/Archives/edgar/data/796343/000079634321000004/0000796343-21-000004-index.htm",
    "finalLink": "https://www.sec.gov/Archives/edgar/data/796343/000079634321000004/adbe-20201127.htm"
  },
  {
    "date": "2019-11-29",
    "symbol": "ADBE",
    "reportedCurrency": "USD",
    "cik": "0000796343",
    "fillingDate": "2020-01-21",
    "acceptedDate": "2020-01-21 06:06:41",
    "calendarYear": "2019",
    "period": "FY",
    "netIncome": 2951458000,
    "depreciationAndAmortization": 624748000,
    "deferredIncomeTax": 2707000,
    "stockBasedCompensation": 787706000,
    "changeInWorkingCapital": 105028000,
    "accountsReceivables": -187826000,
    "inventory": 164697000,
    "accountsPayables": 23129000,
    "otherWorkingCapital": 105028000,
    "otherNonCashItems": -50333000,
    "netCashProvidedByOperatingActivities": 4421314000,
    "investmentsInPropertyPlantAndEquipment": -333981000,
    "acquisitionsNet": -100704000,
    "purchasesOfInvestments": -243192000,
    "salesMaturitiesOfInvestments": 788227000,
    "otherInvestingActivites": -565435000,
    "netCashUsedForInvestingActivites": -455085000,
    "debtRepayment": 0,
    "commonStockIssued": 232932000,
    "commonStockRepurchased": -2750000000,
    "dividendsPaid": 0,
    "otherFinancingActivites": -429044000,
    "netCashUsedProvidedByFinancingActivities": -2946044000,
    "effectOfForexChangesOnCash": -12739000,
    "netChangeInCash": 1007446000,
    "cashAtEndOfPeriod": 2650221000,
    "cashAtBeginningOfPeriod": 1642775000,
    "operatingCashFlow": 4421314000,
    "capitalExpenditure": -333981000,
    "freeCashFlow": 4087333000,
    "link": "https://www.sec.gov/Archives/edgar/data/796343/000079634320000013/0000796343-20-000013-index.htm",
    "finalLink": "https://www.sec.gov/Archives/edgar/data/796343/000079634320000013/adbe10kfy19.htm"
  },
  {
    "date": "2018-11-30",
    "symbol": "ADBE",
    "reportedCurrency": "USD",
    "cik": "0000796343",
    "fillingDate": "2019-01-25",
    "acceptedDate": "2019-01-25 06:24:29",
    "calendarYear": "2018",
    "period": "FY",
    "netIncome": 2590774000,
    "depreciationAndAmortization": 346492000,
    "deferredIncomeTax": -468936000,
    "stockBasedCompensation": 603470000,
    "changeInWorkingCapital": 487775000,
    "accountsReceivables": -1983000,
    "inventory": 445796000,
    "accountsPayables": 54920000,
    "otherWorkingCapital": -10958000,
    "otherNonCashItems": 469729000,
    "netCashProvidedByOperatingActivities": 4029304000,
    "investmentsInPropertyPlantAndEquipment": -266579000,
    "acquisitionsNet": -6314382000,
    "purchasesOfInvestments": -13590000,
    "salesMaturitiesOfInvestments": 1909256000,
    "otherInvestingActivites": 1896000000,
    "netCashUsedForInvestingActivites": -4685295000,
    "debtRepayment": 2248000000,
    "commonStockIssued": 190990000,
    "commonStockRepurchased": -2050000000,
    "dividendsPaid": 0,
    "otherFinancingActivites": -394568000,
    "netCashUsedProvidedByFinancingActivities": -5568000,
    "effectOfForexChangesOnCash": -1738000,
    "netChangeInCash": -663297000,
    "cashAtEndOfPeriod": 1642775000,
    "cashAtBeginningOfPeriod": 2306072000,
    "operatingCashFlow": 4029304000,
    "capitalExpenditure": -266579000,
    "freeCashFlow": 3762725000,
    "link": "https://www.sec.gov/Archives/edgar/data/796343/000079634319000019/0000796343-19-000019-index.htm",
    "finalLink": "https://www.sec.gov/Archives/edgar/data/796343/000079634319000019/adbe10kfy18.htm"
  },
  {
    "date": "2017-12-01",
    "symbol": "ADBE",
    "reportedCurrency": "USD",
    "cik": "0000796343",
    "fillingDate": "2018-01-22",
    "acceptedDate": "2018-01-22 16:07:26",
    "calendarYear": "2017",
    "period": "FY",
    "netIncome": 1693954000,
    "depreciationAndAmortization": 325997000,
    "deferredIncomeTax": 51605000,
    "stockBasedCompensation": 451451000,
    "changeInWorkingCapital": 446945000,
    "accountsReceivables": -187173000,
    "inventory": 232359000,
    "accountsPayables": -45186000,
    "otherWorkingCapital": 446945000,
    "otherNonCashItems": -57099000,
    "netCashProvidedByOperatingActivities": 2912853000,
    "investmentsInPropertyPlantAndEquipment": -178122000,
    "acquisitionsNet": -459626000,
    "purchasesOfInvestments": -57863000,
    "salesMaturitiesOfInvestments": 2155800000,
    "otherInvestingActivites": -1903066000,
    "netCashUsedForInvestingActivites": -442877000,
    "debtRepayment": 0,
    "commonStockIssued": 158351000,
    "commonStockRepurchased": -1100000000,
    "dividendsPaid": 0,
    "otherFinancingActivites": -242086000,
    "netCashUsedProvidedByFinancingActivities": -1183735000,
    "effectOfForexChangesOnCash": 8516000,
    "netChangeInCash": 1294757000,
    "cashAtEndOfPeriod": 2306072000,
    "cashAtBeginningOfPeriod": 1011315000,
    "operatingCashFlow": 2912853000,
    "capitalExpenditure": -178122000,
    "freeCashFlow": 2734731000,
    "link": "https://www.sec.gov/Archives/edgar/data/796343/000079634318000015/0000796343-18-000015-index.htm",
    "finalLink": "https://www.sec.gov/Archives/edgar/data/796343/000079634318000015/adbe10kfy17.htm"
  },
  {
    "date": "2016-12-02",
    "symbol": "ADBE",
    "reportedCurrency": "USD",
    "cik": "0000796343",
    "fillingDate": "2017-01-20",
    "acceptedDate": "2017-01-20 16:14:43",
    "calendarYear": "2016",
    "period": "FY",
    "netIncome": 1168782000,
    "depreciationAndAmortization": 331535000,
    "deferredIncomeTax": 24222000,
    "stockBasedCompensation": 349909000,
    "changeInWorkingCapital": 346357000,
    "accountsReceivables": -160416000,
    "inventory": 166697000,
    "accountsPayables": -6281000,
    "otherWorkingCapital": 346357000,
    "otherNonCashItems": -21077000,
    "netCashProvidedByOperatingActivities": 2199728000,
    "investmentsInPropertyPlantAndEquipment": -203805000,
    "acquisitionsNet": -48427000,
    "purchasesOfInvestments": -711227000,
    "salesMaturitiesOfInvestments": 1635854000,
    "otherInvestingActivites": -1632428000,
    "netCashUsedForInvestingActivites": -960033000,
    "debtRepayment": -108000,
    "commonStockIssued": 145697000,
    "commonStockRepurchased": -1075000000,
    "dividendsPaid": 0,
    "otherFinancingActivites": -161295000,
    "netCashUsedProvidedByFinancingActivities": -1090706000,
    "effectOfForexChangesOnCash": -14234000,
    "netChangeInCash": 134755000,
    "cashAtEndOfPeriod": 1011315000,
    "cashAtBeginningOfPeriod": 876560000,
    "operatingCashFlow": 2199728000,
    "capitalExpenditure": -203805000,
    "freeCashFlow": 1995923000,
    "link": "https://www.sec.gov/Archives/edgar/data/796343/000079634317000031/0000796343-17-000031-index.htm",
    "finalLink": "https://www.sec.gov/Archives/edgar/data/796343/000079634317000031/adbe10kfy16.htm"
  },
  {
    "date": "2015-11-27",
    "symbol": "ADBE",
    "reportedCurrency": "USD",
    "cik": "0000796343",
    "fillingDate": "2016-01-19",
    "acceptedDate": "2016-01-19 08:05:29",
    "calendarYear": "2015",
    "period": "FY",
    "netIncome": 629551000,
    "depreciationAndAmortization": 339473000,
    "deferredIncomeTax": -69657000,
    "stockBasedCompensation": 335839000,
    "changeInWorkingCapital": 195264000,
    "accountsReceivables": -79502000,
    "inventory": 56632000,
    "accountsPayables": 22870000,
    "otherWorkingCapital": 195264000,
    "otherNonCashItems": 39032000,
    "netCashProvidedByOperatingActivities": 1469502000,
    "investmentsInPropertyPlantAndEquipment": -184936000,
    "acquisitionsNet": -826004000,
    "purchasesOfInvestments": -691140000,
    "salesMaturitiesOfInvestments": 1552415000,
    "otherInvestingActivites": -1338693000,
    "netCashUsedForInvestingActivites": -1488358000,
    "debtRepayment": 387091000,
    "commonStockIssued": 164270000,
    "commonStockRepurchased": -625000000,
    "dividendsPaid": 0,
    "otherFinancingActivites": -127048000,
    "netCashUsedProvidedByFinancingActivities": -200687000,
    "effectOfForexChangesOnCash": -21297000,
    "netChangeInCash": -240840000,
    "cashAtEndOfPeriod": 876560000,
    "cashAtBeginningOfPeriod": 1117400000,
    "operatingCashFlow": 1469502000,
    "capitalExpenditure": -184936000,
    "freeCashFlow": 1284566000,
    "link": "https://www.sec.gov/Archives/edgar/data/796343/000079634316000224/0000796343-16-000224-index.htm",
    "finalLink": "https://www.sec.gov/Archives/edgar/data/796343/000079634316000224/adbe10kfy15.htm"
  }
]